py_sourcemap/__init__.py
py_sourcemap/py_sourcemap.so
py_sourcemap-0.4.0.dist-info/METADATA
py_sourcemap-0.4.0.dist-info/RECORD
py_sourcemap-0.4.0.dist-info/WHEEL
py_sourcemap-0.4.0.dist-info/top_level.txt
