Metadata-Version: 2.1
Name: py-sourcemap
Version: 0.4.0
Summary: A tiny source-map-mappings bindings for python using PyO3
Home-page: https://github.com/LeetCode-OpenSource/py-sourcemap
License: UNKNOWN
Platform: UNKNOWN
Classifier: Development Status :: 4 - Beta
Classifier: Environment :: Console
Classifier: Environment :: Web Environment
Classifier: Intended Audience :: Developers
Classifier: Operating System :: MacOS :: MacOS X
Classifier: Operating System :: Microsoft :: Windows
Classifier: Operating System :: POSIX
Classifier: Programming Language :: Python
Classifier: Programming Language :: Rust
Classifier: License :: OSI Approved :: MIT License
Requires-Dist: wheel
